discord_game
