Metadata-Version: 2.1
Name: discord-game
Version: 0.1.3
Summary: Create a discord game
Home-page: https://github.com/VL07/discord.py-game-engine
Author: VL07
Author-email: victor.lundman.07@gmail.com
License: UNKNOWN
Platform: UNKNOWN
Classifier: Programming Language :: Python :: 3
Classifier: Programming Language :: Python :: 3.7
